mcp_observability/__init__.py
mcp_observability-0.1.2.dist-info/METADATA
mcp_observability-0.1.2.dist-info/WHEEL
mcp_observability-0.1.2.dist-info/RECORD
