Metadata-Version: 2.4
Name: mcp-observability
Version: 0.1.2
Summary: Open, vendor-agnostic observability SDK for Model Context Protocol (MCP) applications
Project-URL: Homepage, https://etalesystems.com
Project-URL: Documentation, https://github.com/anish808/mcp-hack#readme
Project-URL: Repository, https://github.com/anish808/mcp-hack.git
Project-URL: Bug Tracker, https://github.com/anish808/mcp-hack/issues
Project-URL: Dashboard, https://etalesystems.com
Author-email: MCP Observability Team <team@mcp-observability.com>
License-Expression: MIT
Keywords: ai,llm,mcp,monitoring,observability,tracing
Classifier: Development Status :: 4 - Beta
Classifier: Intended Audience :: Developers
Classifier: License :: OSI Approved :: MIT License
Classifier: Programming Language :: Python :: 3
Classifier: Programming Language :: Python :: 3.8
Classifier: Programming Language :: Python :: 3.9
Classifier: Programming Language :: Python :: 3.10
Classifier: Programming Language :: Python :: 3.11
Classifier: Programming Language :: Python :: 3.12
Classifier: Topic :: Software Development :: Libraries :: Python Modules
Classifier: Topic :: System :: Monitoring
Requires-Python: >=3.8
Requires-Dist: requests>=2.25.0
Provides-Extra: dev
Requires-Dist: black; extra == 'dev'
Requires-Dist: flake8; extra == 'dev'
Requires-Dist: isort; extra == 'dev'
Requires-Dist: mypy; extra == 'dev'
Requires-Dist: pytest-cov; extra == 'dev'
Requires-Dist: pytest>=6.0; extra == 'dev'
Requires-Dist: types-requests; extra == 'dev'
